Metadata-Version: 2.1
Name: contool
Version: 0.1.3
Summary: Add a short description here!
Home-page: https://github.com/pyscaffold/pyscaffold/
Author: Kleber Leal
Author-email: kleber.leal@gmail.com
License: mit
Project-URL: Documentation, https://pyscaffold.org/
Platform: any
Classifier: Development Status :: 4 - Beta
Classifier: Programming Language :: Python
Provides-Extra: testing
